{
 "actions": [],
 "allow_rename": 1,
 "creation": "2025-07-24 17:08:19.418189",
 "doctype": "DocType",
 "editable_grid": 1,
 "engine": "InnoDB",
 "field_order": [
  "document_type",
  "received",
  "received_date",
  "remarks"
 ],
 "fields": [
  {
   "columns": 3,
   "fieldname": "document_type",
   "fieldtype": "Select",
   "in_list_view": 1,
   "label": "Document Type",
   "options": "Purchase Order\nDelivery Challan / Invoice\nPacking List\nMaterial Test Certificate (MTC)\nInspection Report\nGate Entry Register / Inward Register\nGRN Document (System-Generated)\nAdvance Shipping Notice (ASN)\nWaybill / Transport Document\nCertificate of Conformance (CoC)\nPhoto Evidence",
   "read_only": 1,
   "reqd": 1
  },
  {
   "columns": 1,
   "default": "0",
   "fieldname": "received",
   "fieldtype": "Check",
   "in_list_view": 1,
   "label": "Received"
  },
  {
   "columns": 1,
   "fieldname": "received_date",
   "fieldtype": "Date",
   "in_list_view": 1,
   "label": "Received Date"
  },
  {
   "columns": 5,
   "fieldname": "remarks",
   "fieldtype": "Small Text",
   "in_list_view": 1,
   "label": "Remarks"
  }
 ],
 "grid_page_length": 50,
 "index_web_pages_for_search": 1,
 "istable": 1,
 "links": [],
 "modified": "2025-07-24 19:26:51.691737",
 "modified_by": "Administrator",
 "module": "Erpnext Trackerx Customization",
 "name": "Goods Receipt Document Checklist",
 "owner": "Administrator",
 "permissions": [],
 "row_format": "Dynamic",
 "sort_field": "modified",
 "sort_order": "DESC",
 "states": []
}